stemmeruz/__init__.py
stemmeruz-0.9.dist-info/LICENSE.txt
stemmeruz-0.9.dist-info/METADATA
stemmeruz-0.9.dist-info/WHEEL
stemmeruz-0.9.dist-info/top_level.txt
stemmeruz-0.9.dist-info/RECORD
