Metadata-Version: 2.1
Name: stemmeruz
Version: 0.9
Summary: This package is desgined to help researcher to find stem of the word package has 2 input parameter, first parameter is input word and second parameter is list of stem lecixon
Home-page: UNKNOWN
Author: Alisher Ismailov Shakirovich, Nilufar Abdurakhmonova
Author-email: alisherismailov1991@gmail.com
License: MIT
Platform: UNKNOWN
Classifier: Programming Language :: Python :: 3
Classifier: License :: OSI Approved :: MIT License
Classifier: Operating System :: OS Independent
License-File: LICENSE.txt
